{
  "id": "9366127b-443f-456d-9d9b-257e1c218cfe",
  "prevId": "c4ba469a-d46c-4c47-babe-3f0ce19f784b",
  "version": "7",
  "dialect": "postgresql",
  "tables": {
    "public.tournaments": {
      "name": "tournaments",
      "schema": "",
      "columns": {
        "id": {
          "name": "id",
          "type": "integer",
          "primaryKey": true,
          "notNull": true
        },
        "name": {
          "name": "name",
          "type": "varchar",
          "primaryKey": false,
          "notNull": true
        },
        "size": {
          "name": "size",
          "type": "integer",
          "primaryKey": false,
          "notNull": true
        },
        "start_time": {
          "name": "start_time",
          "type": "timestamp",
          "primaryKey": false,
          "notNull": true
        },
        "status": {
          "name": "status",
          "type": "tournament_status",
          "typeSchema": "public",
          "primaryKey": false,
          "notNull": true
        },
        "owner": {
          "name": "owner",
          "type": "varchar",
          "primaryKey": false,
          "notNull": true
        },
        "description": {
          "name": "description",
          "type": "varchar",
          "primaryKey": false,
          "notNull": true
        },
        "logo": {
          "name": "logo",
          "type": "varchar",
          "primaryKey": false,
          "notNull": true
        }
      },
      "indexes": {},
      "foreignKeys": {},
      "compositePrimaryKeys": {},
      "uniqueConstraints": {},
      "policies": {},
      "checkConstraints": {},
      "isRLSEnabled": false
    }
  },
  "enums": {
    "public.tournament_status": {
      "name": "tournament_status",
      "schema": "public",
      "values": ["Not Started", "In Progress", "Complete"]
    }
  },
  "schemas": {},
  "sequences": {},
  "roles": {},
  "policies": {},
  "views": {},
  "_meta": {
    "columns": {},
    "schemas": {},
    "tables": {}
  }
}
